{
  "$schema": "http://cyclonedx.org/schema/bom-1.7.schema.json",
  "bomFormat": "CycloneDX",
  "specVersion": "1.7",
  "serialNumber": "urn:uuid:7c25999f-f73b-4cfe-93bc-2bca29fa0334",
  "version": 1,
  "metadata": {
    "timestamp": "2026-07-06T07:01:36Z",
    "tools": {
      "components": [
        {
          "type": "application",
          "author": "anchore",
          "name": "syft",
          "version": "1.46.0"
        }
      ]
    },
    "component": {
      "bom-ref": "717ca7902237c3b2",
      "type": "file",
      "name": "/tmp/tmp.4AZD5Z1UIy/demo.mahocommerce.com-default",
      "licenses": [
        {
          "expression": "OSL-3.0 OR AFL-3.0"
        }
      ]
    }
  }
}
