{"$schema":"http://cyclonedx.org/schema/bom-1.6.schema.json","bomFormat":"CycloneDX","specVersion":"1.6","serialNumber":"urn:uuid:f7a6a414-07d5-4741-a04a-95379ca732bd","version":1,"metadata":{"timestamp":"2026-05-11T10:26:43Z","tools":{"components":[{"type":"application","author":"anchore","name":"syft","version":"1.44.0"}]},"component":{"bom-ref":"f93c9d0b86e982d5","type":"file","name":"/tmp/tmp.jAa742bjGj/maho-phpstan-plugin-v4.2.0"}},"components":[{"bom-ref":"pkg:github/actions/checkout@v4?package-id=a00079d9c8e0bc74","type":"library","name":"actions/checkout","version":"v4","cpe":"cpe:2.3:a:actions\\/checkout:actions\\/checkout:v4:*:*:*:*:*:*:*","purl":"pkg:github/actions/checkout@v4","properties":[{"name":"syft:package:foundBy","value":"github-actions-usage-cataloger"},{"name":"syft:package:type","value":"github-action"},{"name":"syft:package:metadataType","value":"github-actions-use-statement"},{"name":"syft:location:0:path","value":"/.github/workflows/phpstan.yml"}]},{"bom-ref":"pkg:composer/phpstan/phpstan@2.1.38?package-id=2e602c28857cd59b","type":"library","name":"phpstan/phpstan","version":"2.1.38","licenses":[{"license":{"id":"MIT"}}],"cpe":"cpe:2.3:a:phpstan\\/phpstan:phpstan\\/phpstan:2.1.38:*:*:*:*:*:*:*","purl":"pkg:composer/phpstan/phpstan@2.1.38","properties":[{"name":"syft:package:foundBy","value":"php-composer-lock-cataloger"},{"name":"syft:package:language","value":"php"},{"name":"syft:package:type","value":"php-composer"},{"name":"syft:package:metadataType","value":"php-composer-lock-entry"},{"name":"syft:location:0:path","value":"/composer.lock"}]},{"bom-ref":"pkg:github/shivammathur/setup-php@v2?package-id=cd986f2f3601b891","type":"library","name":"shivammathur/setup-php","version":"v2","cpe":"cpe:2.3:a:shivammathur\\/setup-php:shivammathur\\/setup-php:v2:*:*:*:*:*:*:*","purl":"pkg:github/shivammathur/setup-php@v2","properties":[{"name":"syft:package:foundBy","value":"github-actions-usage-cataloger"},{"name":"syft:package:type","value":"github-action"},{"name":"syft:package:metadataType","value":"github-actions-use-statement"},{"name":"syft:cpe23","value":"cpe:2.3:a:shivammathur\\/setup-php:shivammathur\\/setup_php:v2:*:*:*:*:*:*:*"},{"name":"syft:cpe23","value":"cpe:2.3:a:shivammathur\\/setup_php:shivammathur\\/setup-php:v2:*:*:*:*:*:*:*"},{"name":"syft:cpe23","value":"cpe:2.3:a:shivammathur\\/setup_php:shivammathur\\/setup_php:v2:*:*:*:*:*:*:*"},{"name":"syft:cpe23","value":"cpe:2.3:a:shivammathur\\/setup:shivammathur\\/setup-php:v2:*:*:*:*:*:*:*"},{"name":"syft:cpe23","value":"cpe:2.3:a:shivammathur\\/setup:shivammathur\\/setup_php:v2:*:*:*:*:*:*:*"},{"name":"syft:location:0:path","value":"/.github/workflows/phpstan.yml"}]},{"bom-ref":"f23abd314990253e","type":"file","name":"/tmp/tmp.jAa742bjGj/maho-phpstan-plugin-v4.2.0/.github/workflows/phpstan.yml","hashes":[{"alg":"SHA-1","content":"9b1e3319f4d843d991ef53747bd1f687cf1acfcd"},{"alg":"SHA-256","content":"25c609ad0b6a1f4e75ec8c9bb4e74f10e2133975b8167b285743c810263b881f"}]},{"bom-ref":"c8bb62e6bded633e","type":"file","name":"/tmp/tmp.jAa742bjGj/maho-phpstan-plugin-v4.2.0/composer.lock","hashes":[{"alg":"SHA-1","content":"4e4ddea220b20f3a13de4dbe7fde6de3c140f9ac"},{"alg":"SHA-256","content":"ef0c9da489a71e9e16137c96a730a79f78801d216fed01854a43372361640c55"}]}]}
