{
  "$schema": "http://cyclonedx.org/schema/bom-1.6.schema.json",
  "bomFormat": "CycloneDX",
  "specVersion": "1.6",
  "serialNumber": "urn:uuid:f26e3bf1-a34a-4851-ba3b-7d0ed2818674",
  "version": 1,
  "metadata": {
    "timestamp": "2026-06-19T08:26:27Z",
    "tools": {
      "components": [
        {
          "type": "application",
          "author": "anchore",
          "name": "syft",
          "version": "1.45.1"
        }
      ]
    },
    "component": {
      "bom-ref": "91b1b0355d619221",
      "type": "file",
      "name": "/tmp/tmp.pn3G5W3FzL/vscode-default",
      "licenses": [
        {
          "license": {
            "id": "MIT"
          }
        }
      ]
    }
  },
  "components": [
    {
      "bom-ref": "pkg:github/actions/checkout@v6.0.3?package-id=39d5de03cb465a33",
      "type": "library",
      "name": "actions/checkout",
      "version": "v6.0.3",
      "cpe": "cpe:2.3:a:actions\\/checkout:actions\\/checkout:v6.0.3:*:*:*:*:*:*:*",
      "purl": "pkg:github/actions/checkout@v6.0.3",
      "properties": [
        {
          "name": "syft:package:foundBy",
          "value": "github-actions-usage-cataloger"
        },
        {
          "name": "syft:package:type",
          "value": "github-action"
        },
        {
          "name": "syft:package:metadataType",
          "value": "github-actions-use-statement"
        },
        {
          "name": "syft:location:0:path",
          "value": "/.github/workflows/release.yml"
        }
      ]
    },
    {
      "bom-ref": "pkg:github/actions/setup-node@v6.4.0?package-id=30e8d03f99b7f7d0",
      "type": "library",
      "name": "actions/setup-node",
      "version": "v6.4.0",
      "cpe": "cpe:2.3:a:actions\\/setup-node:actions\\/setup-node:v6.4.0:*:*:*:*:*:*:*",
      "purl": "pkg:github/actions/setup-node@v6.4.0",
      "properties": [
        {
          "name": "syft:package:foundBy",
          "value": "github-actions-usage-cataloger"
        },
        {
          "name": "syft:package:type",
          "value": "github-action"
        },
        {
          "name": "syft:package:metadataType",
          "value": "github-actions-use-statement"
        },
        {
          "name": "syft:cpe23",
          "value": "cpe:2.3:a:actions\\/setup-node:actions\\/setup_node:v6.4.0:*:*:*:*:*:*:*"
        },
        {
          "name": "syft:cpe23",
          "value": "cpe:2.3:a:actions\\/setup_node:actions\\/setup-node:v6.4.0:*:*:*:*:*:*:*"
        },
        {
          "name": "syft:cpe23",
          "value": "cpe:2.3:a:actions\\/setup_node:actions\\/setup_node:v6.4.0:*:*:*:*:*:*:*"
        },
        {
          "name": "syft:cpe23",
          "value": "cpe:2.3:a:actions\\/setup:actions\\/setup-node:v6.4.0:*:*:*:*:*:*:*"
        },
        {
          "name": "syft:cpe23",
          "value": "cpe:2.3:a:actions\\/setup:actions\\/setup_node:v6.4.0:*:*:*:*:*:*:*"
        },
        {
          "name": "syft:location:0:path",
          "value": "/.github/workflows/release.yml"
        }
      ]
    },
    {
      "bom-ref": "pkg:npm/balanced-match@1.0.2?package-id=0d7c80c1e227b7e2",
      "type": "library",
      "name": "balanced-match",
      "version": "1.0.2",
      "licenses": [
        {
          "license": {
            "id": "MIT"
          }
        }
      ],
      "cpe": "cpe:2.3:a:balanced-match:balanced-match:1.0.2:*:*:*:*:*:*:*",
      "purl": "pkg:npm/balanced-match@1.0.2",
      "properties": [
        {
          "name": "syft:package:foundBy",
          "value": "javascript-lock-cataloger"
        },
        {
          "name": "syft:package:language",
          "value": "javascript"
        },
        {
          "name": "syft:package:type",
          "value": "npm"
        },
        {
          "name": "syft:package:metadataType",
          "value": "javascript-npm-package-lock-entry"
        },
        {
          "name": "syft:cpe23",
          "value": "cpe:2.3:a:balanced-match:balanced_match:1.0.2:*:*:*:*:*:*:*"
        },
        {
          "name": "syft:cpe23",
          "value": "cpe:2.3:a:balanced_match:balanced-match:1.0.2:*:*:*:*:*:*:*"
        },
        {
          "name": "syft:cpe23",
          "value": "cpe:2.3:a:balanced_match:balanced_match:1.0.2:*:*:*:*:*:*:*"
        },
        {
          "name": "syft:cpe23",
          "value": "cpe:2.3:a:balanced:balanced-match:1.0.2:*:*:*:*:*:*:*"
        },
        {
          "name": "syft:cpe23",
          "value": "cpe:2.3:a:balanced:balanced_match:1.0.2:*:*:*:*:*:*:*"
        },
        {
          "name": "syft:location:0:path",
          "value": "/package-lock.json"
        }
      ]
    },
    {
      "bom-ref": "pkg:npm/brace-expansion@2.0.3?package-id=994d1cf4d70bda13",
      "type": "library",
      "name": "brace-expansion",
      "version": "2.0.3",
      "licenses": [
        {
          "license": {
            "id": "MIT"
          }
        }
      ],
      "cpe": "cpe:2.3:a:juliangruber:brace-expansion:2.0.3:*:*:*:*:node.js:*:*",
      "purl": "pkg:npm/brace-expansion@2.0.3",
      "properties": [
        {
          "name": "syft:package:foundBy",
          "value": "javascript-lock-cataloger"
        },
        {
          "name": "syft:package:language",
          "value": "javascript"
        },
        {
          "name": "syft:package:type",
          "value": "npm"
        },
        {
          "name": "syft:package:metadataType",
          "value": "javascript-npm-package-lock-entry"
        },
        {
          "name": "syft:location:0:path",
          "value": "/package-lock.json"
        }
      ]
    },
    {
      "bom-ref": "pkg:npm/maho@0.10.5?package-id=4d26aa0b1f24f35c",
      "type": "library",
      "name": "maho",
      "version": "0.10.5",
      "licenses": [
        {
          "license": {
            "id": "MIT"
          }
        }
      ],
      "cpe": "cpe:2.3:a:maho:maho:0.10.5:*:*:*:*:*:*:*",
      "purl": "pkg:npm/maho@0.10.5",
      "properties": [
        {
          "name": "syft:package:foundBy",
          "value": "javascript-lock-cataloger"
        },
        {
          "name": "syft:package:language",
          "value": "javascript"
        },
        {
          "name": "syft:package:type",
          "value": "npm"
        },
        {
          "name": "syft:package:metadataType",
          "value": "javascript-npm-package-lock-entry"
        },
        {
          "name": "syft:location:0:path",
          "value": "/package-lock.json"
        }
      ]
    },
    {
      "bom-ref": "pkg:npm/minimatch@5.1.9?package-id=6f2feaadcd9ee1df",
      "type": "library",
      "name": "minimatch",
      "version": "5.1.9",
      "licenses": [
        {
          "license": {
            "id": "ISC"
          }
        }
      ],
      "cpe": "cpe:2.3:a:minimatch_project:minimatch:5.1.9:*:*:*:*:node.js:*:*",
      "purl": "pkg:npm/minimatch@5.1.9",
      "properties": [
        {
          "name": "syft:package:foundBy",
          "value": "javascript-lock-cataloger"
        },
        {
          "name": "syft:package:language",
          "value": "javascript"
        },
        {
          "name": "syft:package:type",
          "value": "npm"
        },
        {
          "name": "syft:package:metadataType",
          "value": "javascript-npm-package-lock-entry"
        },
        {
          "name": "syft:location:0:path",
          "value": "/package-lock.json"
        }
      ]
    },
    {
      "bom-ref": "pkg:npm/semver@7.7.4?package-id=dc47801cc9b2ec78",
      "type": "library",
      "name": "semver",
      "version": "7.7.4",
      "licenses": [
        {
          "license": {
            "id": "ISC"
          }
        }
      ],
      "cpe": "cpe:2.3:a:npmjs:semver:7.7.4:*:*:*:*:node.js:*:*",
      "purl": "pkg:npm/semver@7.7.4",
      "properties": [
        {
          "name": "syft:package:foundBy",
          "value": "javascript-lock-cataloger"
        },
        {
          "name": "syft:package:language",
          "value": "javascript"
        },
        {
          "name": "syft:package:type",
          "value": "npm"
        },
        {
          "name": "syft:package:metadataType",
          "value": "javascript-npm-package-lock-entry"
        },
        {
          "name": "syft:location:0:path",
          "value": "/package-lock.json"
        }
      ]
    },
    {
      "bom-ref": "pkg:npm/vscode-jsonrpc@8.2.0?package-id=cf0e7f9314b5d205",
      "type": "library",
      "name": "vscode-jsonrpc",
      "version": "8.2.0",
      "licenses": [
        {
          "license": {
            "id": "MIT"
          }
        }
      ],
      "cpe": "cpe:2.3:a:vscode-jsonrpc:vscode-jsonrpc:8.2.0:*:*:*:*:*:*:*",
      "purl": "pkg:npm/vscode-jsonrpc@8.2.0",
      "properties": [
        {
          "name": "syft:package:foundBy",
          "value": "javascript-lock-cataloger"
        },
        {
          "name": "syft:package:language",
          "value": "javascript"
        },
        {
          "name": "syft:package:type",
          "value": "npm"
        },
        {
          "name": "syft:package:metadataType",
          "value": "javascript-npm-package-lock-entry"
        },
        {
          "name": "syft:cpe23",
          "value": "cpe:2.3:a:vscode-jsonrpc:vscode_jsonrpc:8.2.0:*:*:*:*:*:*:*"
        },
        {
          "name": "syft:cpe23",
          "value": "cpe:2.3:a:vscode_jsonrpc:vscode-jsonrpc:8.2.0:*:*:*:*:*:*:*"
        },
        {
          "name": "syft:cpe23",
          "value": "cpe:2.3:a:vscode_jsonrpc:vscode_jsonrpc:8.2.0:*:*:*:*:*:*:*"
        },
        {
          "name": "syft:cpe23",
          "value": "cpe:2.3:a:vscode:vscode-jsonrpc:8.2.0:*:*:*:*:*:*:*"
        },
        {
          "name": "syft:cpe23",
          "value": "cpe:2.3:a:vscode:vscode_jsonrpc:8.2.0:*:*:*:*:*:*:*"
        },
        {
          "name": "syft:location:0:path",
          "value": "/package-lock.json"
        }
      ]
    },
    {
      "bom-ref": "pkg:npm/vscode-languageclient@9.0.1?package-id=c10f359f7ebb0cb1",
      "type": "library",
      "name": "vscode-languageclient",
      "version": "9.0.1",
      "licenses": [
        {
          "license": {
            "id": "MIT"
          }
        }
      ],
      "cpe": "cpe:2.3:a:vscode-languageclient:vscode-languageclient:9.0.1:*:*:*:*:*:*:*",
      "purl": "pkg:npm/vscode-languageclient@9.0.1",
      "properties": [
        {
          "name": "syft:package:foundBy",
          "value": "javascript-lock-cataloger"
        },
        {
          "name": "syft:package:language",
          "value": "javascript"
        },
        {
          "name": "syft:package:type",
          "value": "npm"
        },
        {
          "name": "syft:package:metadataType",
          "value": "javascript-npm-package-lock-entry"
        },
        {
          "name": "syft:cpe23",
          "value": "cpe:2.3:a:vscode-languageclient:vscode_languageclient:9.0.1:*:*:*:*:*:*:*"
        },
        {
          "name": "syft:cpe23",
          "value": "cpe:2.3:a:vscode_languageclient:vscode-languageclient:9.0.1:*:*:*:*:*:*:*"
        },
        {
          "name": "syft:cpe23",
          "value": "cpe:2.3:a:vscode_languageclient:vscode_languageclient:9.0.1:*:*:*:*:*:*:*"
        },
        {
          "name": "syft:cpe23",
          "value": "cpe:2.3:a:vscode:vscode-languageclient:9.0.1:*:*:*:*:*:*:*"
        },
        {
          "name": "syft:cpe23",
          "value": "cpe:2.3:a:vscode:vscode_languageclient:9.0.1:*:*:*:*:*:*:*"
        },
        {
          "name": "syft:location:0:path",
          "value": "/package-lock.json"
        }
      ]
    },
    {
      "bom-ref": "pkg:npm/vscode-languageserver-protocol@3.17.5?package-id=39528849d6581bbf",
      "type": "library",
      "name": "vscode-languageserver-protocol",
      "version": "3.17.5",
      "licenses": [
        {
          "license": {
            "id": "MIT"
          }
        }
      ],
      "cpe": "cpe:2.3:a:vscode-languageserver-protocol:vscode-languageserver-protocol:3.17.5:*:*:*:*:*:*:*",
      "purl": "pkg:npm/vscode-languageserver-protocol@3.17.5",
      "properties": [
        {
          "name": "syft:package:foundBy",
          "value": "javascript-lock-cataloger"
        },
        {
          "name": "syft:package:language",
          "value": "javascript"
        },
        {
          "name": "syft:package:type",
          "value": "npm"
        },
        {
          "name": "syft:package:metadataType",
          "value": "javascript-npm-package-lock-entry"
        },
        {
          "name": "syft:cpe23",
          "value": "cpe:2.3:a:vscode-languageserver-protocol:vscode_languageserver_protocol:3.17.5:*:*:*:*:*:*:*"
        },
        {
          "name": "syft:cpe23",
          "value": "cpe:2.3:a:vscode_languageserver_protocol:vscode-languageserver-protocol:3.17.5:*:*:*:*:*:*:*"
        },
        {
          "name": "syft:cpe23",
          "value": "cpe:2.3:a:vscode_languageserver_protocol:vscode_languageserver_protocol:3.17.5:*:*:*:*:*:*:*"
        },
        {
          "name": "syft:cpe23",
          "value": "cpe:2.3:a:vscode-languageserver:vscode-languageserver-protocol:3.17.5:*:*:*:*:*:*:*"
        },
        {
          "name": "syft:cpe23",
          "value": "cpe:2.3:a:vscode-languageserver:vscode_languageserver_protocol:3.17.5:*:*:*:*:*:*:*"
        },
        {
          "name": "syft:cpe23",
          "value": "cpe:2.3:a:vscode_languageserver:vscode-languageserver-protocol:3.17.5:*:*:*:*:*:*:*"
        },
        {
          "name": "syft:cpe23",
          "value": "cpe:2.3:a:vscode_languageserver:vscode_languageserver_protocol:3.17.5:*:*:*:*:*:*:*"
        },
        {
          "name": "syft:cpe23",
          "value": "cpe:2.3:a:vscode:vscode-languageserver-protocol:3.17.5:*:*:*:*:*:*:*"
        },
        {
          "name": "syft:cpe23",
          "value": "cpe:2.3:a:vscode:vscode_languageserver_protocol:3.17.5:*:*:*:*:*:*:*"
        },
        {
          "name": "syft:location:0:path",
          "value": "/package-lock.json"
        }
      ]
    },
    {
      "bom-ref": "pkg:npm/vscode-languageserver-types@3.17.5?package-id=e2cf673f4864441e",
      "type": "library",
      "name": "vscode-languageserver-types",
      "version": "3.17.5",
      "licenses": [
        {
          "license": {
            "id": "MIT"
          }
        }
      ],
      "cpe": "cpe:2.3:a:vscode-languageserver-types:vscode-languageserver-types:3.17.5:*:*:*:*:*:*:*",
      "purl": "pkg:npm/vscode-languageserver-types@3.17.5",
      "properties": [
        {
          "name": "syft:package:foundBy",
          "value": "javascript-lock-cataloger"
        },
        {
          "name": "syft:package:language",
          "value": "javascript"
        },
        {
          "name": "syft:package:type",
          "value": "npm"
        },
        {
          "name": "syft:package:metadataType",
          "value": "javascript-npm-package-lock-entry"
        },
        {
          "name": "syft:cpe23",
          "value": "cpe:2.3:a:vscode-languageserver-types:vscode_languageserver_types:3.17.5:*:*:*:*:*:*:*"
        },
        {
          "name": "syft:cpe23",
          "value": "cpe:2.3:a:vscode_languageserver_types:vscode-languageserver-types:3.17.5:*:*:*:*:*:*:*"
        },
        {
          "name": "syft:cpe23",
          "value": "cpe:2.3:a:vscode_languageserver_types:vscode_languageserver_types:3.17.5:*:*:*:*:*:*:*"
        },
        {
          "name": "syft:cpe23",
          "value": "cpe:2.3:a:vscode-languageserver:vscode-languageserver-types:3.17.5:*:*:*:*:*:*:*"
        },
        {
          "name": "syft:cpe23",
          "value": "cpe:2.3:a:vscode-languageserver:vscode_languageserver_types:3.17.5:*:*:*:*:*:*:*"
        },
        {
          "name": "syft:cpe23",
          "value": "cpe:2.3:a:vscode_languageserver:vscode-languageserver-types:3.17.5:*:*:*:*:*:*:*"
        },
        {
          "name": "syft:cpe23",
          "value": "cpe:2.3:a:vscode_languageserver:vscode_languageserver_types:3.17.5:*:*:*:*:*:*:*"
        },
        {
          "name": "syft:cpe23",
          "value": "cpe:2.3:a:vscode:vscode-languageserver-types:3.17.5:*:*:*:*:*:*:*"
        },
        {
          "name": "syft:cpe23",
          "value": "cpe:2.3:a:vscode:vscode_languageserver_types:3.17.5:*:*:*:*:*:*:*"
        },
        {
          "name": "syft:location:0:path",
          "value": "/package-lock.json"
        }
      ]
    },
    {
      "bom-ref": "cc210d8a1a5f5704",
      "type": "file",
      "name": "/tmp/tmp.pn3G5W3FzL/vscode-default/.github/workflows/release.yml",
      "hashes": [
        {
          "alg": "SHA-1",
          "content": "8b130114d645984bd0df7e7200046a5059a91476"
        },
        {
          "alg": "SHA-256",
          "content": "e27518ae87ceebda15ac4142a9b33bd189ac5425788954f6a33898056fcdab58"
        }
      ]
    },
    {
      "bom-ref": "fd71c2238fc07657",
      "type": "file",
      "name": "/tmp/tmp.pn3G5W3FzL/vscode-default/package-lock.json",
      "hashes": [
        {
          "alg": "SHA-1",
          "content": "4e1cb96cc74021d30e8cc98aaa65bc7bfa0230ed"
        },
        {
          "alg": "SHA-256",
          "content": "0e42dbd8d1a1367a9a70152b02d83009723b2d762db6fd8385fc0c00eeed6c03"
        }
      ]
    }
  ],
  "dependencies": [
    {
      "ref": "pkg:npm/brace-expansion@2.0.3?package-id=994d1cf4d70bda13",
      "dependsOn": [
        "pkg:npm/balanced-match@1.0.2?package-id=0d7c80c1e227b7e2"
      ]
    },
    {
      "ref": "pkg:npm/maho@0.10.5?package-id=4d26aa0b1f24f35c",
      "dependsOn": [
        "pkg:npm/vscode-languageclient@9.0.1?package-id=c10f359f7ebb0cb1"
      ]
    },
    {
      "ref": "pkg:npm/minimatch@5.1.9?package-id=6f2feaadcd9ee1df",
      "dependsOn": [
        "pkg:npm/brace-expansion@2.0.3?package-id=994d1cf4d70bda13"
      ]
    },
    {
      "ref": "pkg:npm/vscode-languageclient@9.0.1?package-id=c10f359f7ebb0cb1",
      "dependsOn": [
        "pkg:npm/minimatch@5.1.9?package-id=6f2feaadcd9ee1df",
        "pkg:npm/semver@7.7.4?package-id=dc47801cc9b2ec78",
        "pkg:npm/vscode-languageserver-protocol@3.17.5?package-id=39528849d6581bbf"
      ]
    },
    {
      "ref": "pkg:npm/vscode-languageserver-protocol@3.17.5?package-id=39528849d6581bbf",
      "dependsOn": [
        "pkg:npm/vscode-jsonrpc@8.2.0?package-id=cf0e7f9314b5d205",
        "pkg:npm/vscode-languageserver-types@3.17.5?package-id=e2cf673f4864441e"
      ]
    }
  ]
}
